mirzapkg/__init__.py
mirzapkg/anbar.py
mirzapkg/instaNoche.py
mirzapkg/mirza.py
mirzapkg/netnoche.py
mirzapkg/noche.py
mirzapkg-0.0.1.dist-info/LICENSE
mirzapkg-0.0.1.dist-info/METADATA
mirzapkg-0.0.1.dist-info/WHEEL
mirzapkg-0.0.1.dist-info/top_level.txt
mirzapkg-0.0.1.dist-info/RECORD
