Metadata-Version: 2.1
Name: mirzapkg
Version: 0.0.1
Summary: A helper package
Home-page: https://github.com/tp1050/mirza.git
Author: kp
Author-email: panahikaren91@gmail.com
License: UNKNOWN
Project-URL: Bug Tracker, https://github.com/pypa/sampleproject/issues
Platform: UNKNOWN
Classifier: Programming Language :: Python :: 3
Classifier: License :: OSI Approved :: MIT License
Classifier: Operating System :: OS Independent
Requires-Python: >=3.6
License-File: LICENSE
